{"id":"92gcStu1oJGfHo8IEdN5YF","name":"dq_SAPMaterialText","description":null,"documentType":"RULE_SPECIFICATION","repoInfo":{"repoPath":"","repoHandle":"92gcStu1oJGfHo8IEdN5YF"},"docRef":null,"customAttributes":{"stringAttrs":[{"name":"ReferencedPublishingAllowed","value":"true"},{"name":"DIMENSION","value":"CONSISTENCY"},{"name":"EXCEPTION","value":"false"}]},"nativeData":{"id":"92gcStu1oJGfHo8IEdN5YF","documentBlob":"{\"inputFields\":[{\"name\":\"gasProduct\",\"type\":\"string\",\"precision\":50,\"scale\":0,\"id\":\"117d1972-9951-438b-9dfa-a24fe552f737\"},{\"name\":\"Grade\",\"type\":\"string\",\"precision\":50,\"scale\":0,\"id\":\"79760b1d-a69c-40f3-b67e-1fb54da2da6f\"}],\"outputFields\":[{\"name\":\"PrimaryRuleSet\",\"id\":\"e9082258-a7da-4328-87c4-3a9a6717d93d\",\"type\":\"string\",\"precision\":\"100\",\"scale\":0}],\"ruleModel\":\"{\\\"$$class\\\":\\\"com.informatica.dq.rulebuilder.RuleDefinition\\\",\\\"$$IID\\\":\\\"92gcStu1oJGfHo8IEdN5YF\\\",\\\"name\\\":\\\"dq_SAPMaterialText\\\",\\\"$$id\\\":\\\"92gcStu1oJGfHo8IEdN5YF\\\",\\\"outsideValidityMessage\\\":\\\"undefined\\\",\\\"validFromDate\\\":\\\"-3600000\\\",\\\"validToDate\\\":\\\"-3600000\\\",\\\"$$aggregator\\\":{\\\"$$lockedOn\\\":0,\\\"$$version\\\":1494513349121,\\\"##IID\\\":\\\"U:IGWzIjZXEeefFIPeKxPNig\\\",\\\"name\\\":\\\"DATES\\\",\\\"$$lockedBy\\\":\\\"\\\",\\\"$$class\\\":789,\\\"$$property\\\":\\\"contents\\\"},\\\"tags\\\":[],\\\"options\\\":[{\\\"$$class\\\":\\\"com.informatica.dq.rulebuilder.StringOption\\\",\\\"name\\\":\\\"DEFAULT_STRING_PRECISION\\\",\\\"optionValue\\\":\\\"100\\\"},{\\\"$$class\\\":\\\"com.informatica.dq.rulebuilder.StringOption\\\",\\\"name\\\":\\\"DEFAULT_DECIMAL_PRECISION\\\",\\\"optionValue\\\":\\\"10\\\"},{\\\"$$class\\\":\\\"com.informatica.dq.rulebuilder.StringOption\\\",\\\"name\\\":\\\"DEFAULT_DECIMAL_SCALE\\\",\\\"optionValue\\\":\\\"4\\\"},{\\\"$$class\\\":\\\"com.informatica.dq.rulebuilder.StringOption\\\",\\\"name\\\":\\\"DIMENSION\\\",\\\"optionValue\\\":\\\"NONE\\\"},{\\\"$$class\\\":\\\"com.informatica.dq.rulebuilder.StringOption\\\",\\\"name\\\":\\\"EXCEPTION\\\",\\\"optionValue\\\":\\\"false\\\"}],\\\"fields\\\":[{\\\"$$class\\\":\\\"com.informatica.dq.rulebuilder.Field\\\",\\\"$$id\\\":\\\"5\\\",\\\"$$externalID\\\":\\\"117d1972-9951-438b-9dfa-a24fe552f737\\\",\\\"precision\\\":\\\"50\\\",\\\"scale\\\":\\\"0\\\",\\\"name\\\":\\\"gasProduct\\\",\\\"$type\\\":{\\\"##SID\\\":\\\"smd:com.informatica.metadata.seed.platform.Platform.typesystem/string\\\",\\\"$$class\\\":\\\"com.informatica.metadata.common.typesystem.DataType\\\"},\\\"description\\\":\\\"\\\"},{\\\"$$class\\\":\\\"com.informatica.dq.rulebuilder.Field\\\",\\\"$$id\\\":\\\"36\\\",\\\"$$externalID\\\":\\\"79760b1d-a69c-40f3-b67e-1fb54da2da6f\\\",\\\"precision\\\":\\\"50\\\",\\\"scale\\\":\\\"0\\\",\\\"name\\\":\\\"Grade\\\",\\\"$type\\\":{\\\"##SID\\\":\\\"smd:com.informatica.metadata.seed.platform.Platform.typesystem/string\\\",\\\"$$class\\\":\\\"com.informatica.metadata.common.typesystem.DataType\\\"},\\\"description\\\":\\\"\\\"},{\\\"$$class\\\":\\\"com.informatica.dq.rulebuilder.Field\\\",\\\"$$id\\\":\\\"37\\\",\\\"$$externalID\\\":\\\"10ba7403-54a4-462f-808b-d6770bf275bc\\\",\\\"precision\\\":\\\"50\\\",\\\"scale\\\":\\\"0\\\",\\\"name\\\":\\\"INTCode\\\",\\\"$type\\\":{\\\"##SID\\\":\\\"smd:com.informatica.metadata.seed.platform.Platform.typesystem/string\\\",\\\"$$class\\\":\\\"com.informatica.metadata.common.typesystem.DataType\\\"},\\\"description\\\":\\\"\\\"},{\\\"$$class\\\":\\\"com.informatica.dq.rulebuilder.Field\\\",\\\"$$id\\\":\\\"38\\\",\\\"$$externalID\\\":\\\"d544f692-4603-48c9-966a-eef3d441a49b\\\",\\\"precision\\\":\\\"50\\\",\\\"scale\\\":\\\"0\\\",\\\"name\\\":\\\"GradeID\\\",\\\"$type\\\":{\\\"##SID\\\":\\\"smd:com.informatica.metadata.seed.platform.Platform.typesystem/string\\\",\\\"$$class\\\":\\\"com.informatica.metadata.common.typesystem.DataType\\\"},\\\"description\\\":\\\"\\\"},{\\\"$$class\\\":\\\"com.informatica.dq.rulebuilder.Field\\\",\\\"$$id\\\":\\\"39\\\",\\\"$$externalID\\\":\\\"a69bfe9f-49a5-4409-8936-c16198fb76ac\\\",\\\"precision\\\":\\\"50\\\",\\\"scale\\\":\\\"0\\\",\\\"name\\\":\\\"Format\\\",\\\"$type\\\":{\\\"##SID\\\":\\\"smd:com.informatica.metadata.seed.platform.Platform.typesystem/string\\\",\\\"$$class\\\":\\\"com.informatica.metadata.common.typesystem.DataType\\\"},\\\"description\\\":\\\"\\\"}],\\\"outputFields\\\":[],\\\"testData\\\":[{\\\"field\\\":{\\\"name\\\":\\\"gasProduct\\\",\\\"$$class\\\":\\\"com.informatica.dq.rulebuilder.Field\\\",\\\"##id\\\":\\\"5\\\",\\\"##externalID\\\":\\\"117d1972-9951-438b-9dfa-a24fe552f737\\\"},\\\"testData\\\":[\\\"\\\",\\\"\\\",\\\"\\\",\\\"\\\",\\\"\\\",\\\"\\\",\\\"\\\",\\\"\\\",\\\"\\\",\\\"\\\",\\\"\\\",\\\"\\\",\\\"\\\",\\\"\\\",\\\"\\\",\\\"\\\",\\\"\\\",\\\"\\\",\\\"\\\",\\\"\\\",\\\"\\\",\\\"\\\",\\\"\\\",\\\"\\\",\\\"\\\",\\\"\\\",\\\"\\\",\\\"\\\",\\\"\\\",\\\"\\\",\\\"\\\",\\\"\\\",\\\"\\\",\\\"\\\",\\\"\\\",\\\"\\\",\\\"\\\",\\\"\\\",\\\"\\\",\\\"\\\",\\\"\\\",\\\"\\\",\\\"\\\",\\\"\\\",\\\"\\\",\\\"\\\",\\\"\\\",\\\"\\\",\\\"\\\",\\\"\\\"]},{\\\"field\\\":{\\\"name\\\":\\\"Grade\\\",\\\"$$class\\\":\\\"com.informatica.dq.rulebuilder.Field\\\",\\\"##id\\\":\\\"36\\\",\\\"##externalID\\\":\\\"79760b1d-a69c-40f3-b67e-1fb54da2da6f\\\"},\\\"testData\\\":[\\\"\\\",\\\"\\\",\\\"\\\",\\\"\\\",\\\"\\\",\\\"\\\",\\\"\\\",\\\"\\\",\\\"\\\",\\\"\\\",\\\"\\\",\\\"\\\",\\\"\\\",\\\"\\\",\\\"\\\",\\\"\\\",\\\"\\\",\\\"\\\",\\\"\\\",\\\"\\\",\\\"\\\",\\\"\\\",\\\"\\\",\\\"\\\",\\\"\\\",\\\"\\\",\\\"\\\",\\\"\\\",\\\"\\\",\\\"\\\",\\\"\\\",\\\"\\\",\\\"\\\",\\\"\\\",\\\"\\\",\\\"\\\",\\\"\\\",\\\"\\\",\\\"\\\",\\\"\\\",\\\"\\\",\\\"\\\",\\\"\\\",\\\"\\\",\\\"\\\",\\\"\\\",\\\"\\\",\\\"\\\",\\\"\\\",\\\"\\\"]},{\\\"field\\\":{\\\"name\\\":\\\"INTCode\\\",\\\"$$class\\\":\\\"com.informatica.dq.rulebuilder.Field\\\",\\\"##id\\\":\\\"37\\\",\\\"##externalID\\\":\\\"10ba7403-54a4-462f-808b-d6770bf275bc\\\"},\\\"testData\\\":[\\\"\\\",\\\"\\\",\\\"\\\",\\\"\\\",\\\"\\\",\\\"\\\",\\\"\\\",\\\"\\\",\\\"\\\",\\\"\\\",\\\"\\\",\\\"\\\",\\\"\\\",\\\"\\\",\\\"\\\",\\\"\\\",\\\"\\\",\\\"\\\",\\\"\\\",\\\"\\\",\\\"\\\",\\\"\\\",\\\"\\\",\\\"\\\",\\\"\\\",\\\"\\\",\\\"\\\",\\\"\\\",\\\"\\\",\\\"\\\",\\\"\\\",\\\"\\\",\\\"\\\",\\\"\\\",\\\"\\\",\\\"\\\",\\\"\\\",\\\"\\\",\\\"\\\",\\\"\\\",\\\"\\\",\\\"\\\",\\\"\\\",\\\"\\\",\\\"\\\",\\\"\\\",\\\"\\\",\\\"\\\",\\\"\\\",\\\"\\\"]},{\\\"field\\\":{\\\"name\\\":\\\"GradeID\\\",\\\"$$class\\\":\\\"com.informatica.dq.rulebuilder.Field\\\",\\\"##id\\\":\\\"38\\\",\\\"##externalID\\\":\\\"d544f692-4603-48c9-966a-eef3d441a49b\\\"},\\\"testData\\\":[\\\"\\\",\\\"\\\",\\\"\\\",\\\"\\\",\\\"\\\",\\\"\\\",\\\"\\\",\\\"\\\",\\\"\\\",\\\"\\\",\\\"\\\",\\\"\\\",\\\"\\\",\\\"\\\",\\\"\\\",\\\"\\\",\\\"\\\",\\\"\\\",\\\"\\\",\\\"\\\",\\\"\\\",\\\"\\\",\\\"\\\",\\\"\\\",\\\"\\\",\\\"\\\",\\\"\\\",\\\"\\\",\\\"\\\",\\\"\\\",\\\"\\\",\\\"\\\",\\\"\\\",\\\"\\\",\\\"\\\",\\\"\\\",\\\"\\\",\\\"\\\",\\\"\\\",\\\"\\\",\\\"\\\",\\\"\\\",\\\"\\\",\\\"\\\",\\\"\\\",\\\"\\\",\\\"\\\",\\\"\\\",\\\"\\\",\\\"\\\"]},{\\\"field\\\":{\\\"name\\\":\\\"Format\\\",\\\"$$class\\\":\\\"com.informatica.dq.rulebuilder.Field\\\",\\\"##id\\\":\\\"39\\\",\\\"##externalID\\\":\\\"a69bfe9f-49a5-4409-8936-c16198fb76ac\\\"},\\\"testData\\\":[\\\"\\\",\\\"\\\",\\\"\\\",\\\"\\\",\\\"\\\",\\\"\\\",\\\"\\\",\\\"\\\",\\\"\\\",\\\"\\\",\\\"\\\",\\\"\\\",\\\"\\\",\\\"\\\",\\\"\\\",\\\"\\\",\\\"\\\",\\\"\\\",\\\"\\\",\\\"\\\",\\\"\\\",\\\"\\\",\\\"\\\",\\\"\\\",\\\"\\\",\\\"\\\",\\\"\\\",\\\"\\\",\\\"\\\",\\\"\\\",\\\"\\\",\\\"\\\",\\\"\\\",\\\"\\\",\\\"\\\",\\\"\\\",\\\"\\\",\\\"\\\",\\\"\\\",\\\"\\\",\\\"\\\",\\\"\\\",\\\"\\\",\\\"\\\",\\\"\\\",\\\"\\\",\\\"\\\",\\\"\\\",\\\"\\\",\\\"\\\"]}],\\\"topRuleFamily\\\":{\\\"$$class\\\":\\\"com.informatica.dq.rulebuilder.RuleFamily\\\",\\\"name\\\":\\\"PrimaryRuleSet\\\",\\\"description\\\":\\\"\\\",\\\"$$id\\\":\\\"6\\\",\\\"$$externalID\\\":\\\"e9082258-a7da-4328-87c4-3a9a6717d93d\\\",\\\"outputs\\\":[],\\\"outputLinks\\\":[],\\\"statements\\\":[{\\\"$$class\\\":\\\"com.informatica.dq.rulebuilder.Statement\\\",\\\"action\\\":{\\\"$$class\\\":\\\"com.informatica.dq.rulebuilder.Operation\\\",\\\"$$id\\\":\\\"7\\\",\\\"name\\\":\\\"Expression\\\",\\\"description\\\":\\\"\\\",\\\"type\\\":\\\"Expression\\\",\\\"options\\\":[{\\\"$$class\\\":\\\"com.informatica.dq.rulebuilder.StringOption\\\",\\\"name\\\":\\\"expressionString\\\",\\\"optionValue\\\":\\\"Concat( Upper(Grade) , Upper(gasProduct))\\\"},{\\\"$$class\\\":\\\"com.informatica.dq.rulebuilder.StringOption\\\",\\\"name\\\":\\\"CustomExpression\\\",\\\"optionValue\\\":\\\"CustomExpression\\\"},{\\\"$$class\\\":\\\"com.informatica.dq.rulebuilder.StringOption\\\",\\\"name\\\":\\\"0\\\",\\\"optionValue\\\":\\\"gasProduct\\\"},{\\\"$$class\\\":\\\"com.informatica.dq.rulebuilder.StringOption\\\",\\\"name\\\":\\\"1\\\",\\\"optionValue\\\":\\\"Grade\\\"}],\\\"inputs\\\":[{\\\"name\\\":\\\"gasProduct\\\",\\\"$$class\\\":\\\"com.informatica.dq.rulebuilder.Field\\\",\\\"##id\\\":\\\"5\\\",\\\"##externalID\\\":\\\"117d1972-9951-438b-9dfa-a24fe552f737\\\"},{\\\"name\\\":\\\"Grade\\\",\\\"$$class\\\":\\\"com.informatica.dq.rulebuilder.Field\\\",\\\"##id\\\":\\\"36\\\",\\\"##externalID\\\":\\\"79760b1d-a69c-40f3-b67e-1fb54da2da6f\\\"}],\\\"suboperations\\\":[],\\\"outputs\\\":[]},\\\"condition\\\":{\\\"$$class\\\":\\\"com.informatica.dq.rulebuilder.Operation\\\",\\\"$$id\\\":\\\"8\\\",\\\"name\\\":\\\"NotEquals\\\",\\\"description\\\":\\\"\\\",\\\"type\\\":\\\"NotEquals\\\",\\\"options\\\":[{\\\"$$class\\\":\\\"com.informatica.dq.rulebuilder.StringOption\\\",\\\"name\\\":\\\"useNull\\\",\\\"optionValue\\\":\\\"true\\\"}],\\\"inputs\\\":[{\\\"name\\\":\\\"gasProduct\\\",\\\"$$class\\\":\\\"com.informatica.dq.rulebuilder.Field\\\",\\\"##id\\\":\\\"5\\\",\\\"##externalID\\\":\\\"117d1972-9951-438b-9dfa-a24fe552f737\\\"}],\\\"suboperations\\\":[],\\\"outputs\\\":[]}},{\\\"$$class\\\":\\\"com.informatica.dq.rulebuilder.Statement\\\",\\\"action\\\":{\\\"$$class\\\":\\\"com.informatica.dq.rulebuilder.Operation\\\",\\\"$$id\\\":\\\"9\\\",\\\"name\\\":\\\"\\\",\\\"description\\\":\\\"\\\",\\\"options\\\":[],\\\"inputs\\\":[],\\\"suboperations\\\":[],\\\"outputs\\\":[]},\\\"condition\\\":{\\\"$$class\\\":\\\"com.informatica.dq.rulebuilder.Operation\\\",\\\"$$id\\\":\\\"10\\\",\\\"name\\\":\\\"\\\",\\\"description\\\":\\\"\\\",\\\"type\\\":\\\"DefaultValue\\\",\\\"options\\\":[],\\\"inputs\\\":[],\\\"suboperations\\\":[],\\\"outputs\\\":[]}}],\\\"ruleFamilies\\\":[],\\\"fields\\\":[{\\\"name\\\":\\\"gasProduct\\\",\\\"$$class\\\":\\\"com.informatica.dq.rulebuilder.Field\\\",\\\"##id\\\":\\\"5\\\",\\\"##externalID\\\":\\\"117d1972-9951-438b-9dfa-a24fe552f737\\\"},{\\\"name\\\":\\\"Grade\\\",\\\"$$class\\\":\\\"com.informatica.dq.rulebuilder.Field\\\",\\\"##id\\\":\\\"36\\\",\\\"##externalID\\\":\\\"79760b1d-a69c-40f3-b67e-1fb54da2da6f\\\"}]}}\"}"},"documentState":null}